hancsv/__init__.py
hancsv/hancsv.py
hancsv-1.2.dist-info/METADATA
hancsv-1.2.dist-info/WHEEL
hancsv-1.2.dist-info/top_level.txt
hancsv-1.2.dist-info/RECORD
