Metadata-Version: 2.2
Name: hancsv
Version: 1.2
Summary: A utility for handling CSV files, supports Hancom Cell CSV file (for cybersecurity demo purposes only).
Author: Jaehoon Lee
Author-email: 68533989+jaehoon0905@users.noreply.github.com
Classifier: Programming Language :: Python :: 3
Classifier: Development Status :: 3 - Alpha
Classifier: Environment :: Console
Requires-Python: >=3.6
Dynamic: author
Dynamic: author-email
Dynamic: classifier
Dynamic: description
Dynamic: description-content-type
Dynamic: requires-python
Dynamic: summary
